hicsv/__init__.py
hicsv_python-1.1.0.dist-info/METADATA
hicsv_python-1.1.0.dist-info/WHEEL
hicsv_python-1.1.0.dist-info/licenses/LICENSE
hicsv_python-1.1.0.dist-info/RECORD
