Metadata-Version: 2.4
Name: hicsv-python
Version: 1.1.0
Summary: Python implementation of the Header-Included Comma-Separated Values (hicsv) file format. 
Project-URL: Homepage, https://github.com/shntrnkgw/hicsv
Author-email: Shintaro Nakagawa <shntrnkgw@gmail.com>
License: MIT License
License-File: LICENSE
Classifier: License :: OSI Approved :: MIT License
Classifier: Programming Language :: Python :: 3.10
Classifier: Programming Language :: Python :: 3.11
Classifier: Programming Language :: Python :: 3.12
Classifier: Programming Language :: Python :: 3.13
Requires-Python: >=3.10
Requires-Dist: numpy>=1.23
